{"title":"00. 1wk","markdown":{"yaml":{"title":"00. 1wk","author":"gc","date":"09/11/24"},"headingText":"Intro","containsRefs":false,"markdown":"\n\n\n`1` 3C4P를 2개 정도 잘 정리하자.\n\n`2` 1일 1지원을 목표로! (완벽주의가 아닌 완성주의 마인드 셋)\n\n# 체인지업 기본 참여 마인드셋\n\n`1` GDR-4 중 최합자 vs. 불합격자 비교\n\n- 과제참여도는 전반적으로 높음\n\n- 서류 제출 시기 늦음 : 미최합자의 `62%`는 4주차부터 본격적으로 서류 제출 시작\n    * 완벽주의에 위험성...갖다 버리자\n\n- 3C4P 분해 미흡 : 미최합자의 `50%`는 3C4P 완성도 미흡\n    * **`3C4P`를 `매일 수치화`하고 `매일 디테일`하게 수정하자.**\n    * 포트폴리오도 주차별로 업데이트 하자.(난 매일매일...)\n\n- 중소기업 지원 비율 낮음 : 미최합자의 `50%`는 중소 기업의 지원률이 매우 저조하고 중견이상 지원\n    * 중소기업을 쓰는 이유는 면접 연습이다.\n    * 또한, 다 떨어질 경우를 대비해서 지원하는 것이 좋다.\n- 지원 기업 준비도 미흡 : 미최합자의 `25%`는 각 회사별로 지원동기 작성을 못했거나 포트폴리오 또는 이력서를 자소서보다 우선시 하는 기업 위주로 지원\n\n`2` 결론\n\n- 1주차 부터 지원 시도하자.\n\n- 한번을 하더라도 `영혼을 갈아넣어서` 완성주의 과제를 진행하자.\n\n- 대기업만이 아닌 `대기업도 포함`해서 지원하자.\n\n- 또한, 유튜브도 참고하자.(매일 매일 1개씩 보고 느낀점 기록)\n\n***\n\n# 경험리스트업으로 필살기 발굴\n\n`1` 최종합격자들의 경험리스트업\n\n- 신입은 분류한 총 경험개수 12개, 필살기 경험개수 3개 정도...\n\n`2` 필살기 경험 유형\n\n- 인문계열 경험유형 top3 : `인턴`, 계약직, 아르바이트\n\n- 이공계열 경험유형 top3 : `학교프로젝트`, 연구/개발, 아르바이트\n\n`3` 필살기/KPI 매칭 특징 : `수치화` 가능한 결과물이 있는 경험 `O`\n\n- 인문계열 주요 KPI list : 매출상승(영업), 비용 및 예산준수(회계), 전환율(마케팅)\n\n- 이공계열 주요 KPI list : 불량률 개선(품질관리), 성능개선(공정기술), 프로젝트 완료율(연구개발), 기술스택개선(IT개발)\n\n`4` 최종합격자 경험리스트업케이스 $\\to$ `나에게` 중요한 것이 아닌, `수치화가 된 결과물 위주로 경험 매칭!\n\n- 데이터분석 : KPI 매칭이 1개만 될 경우도 있다. 그래도 걱정하지 말자\n    * 연구개발\n    * 수상경력\n    * 연구개발\n    * 교내 프로젝트\n    * 피드백 : 내가 한 것들을 전부 수치화해서 다시 정리하자  \n\n`6` 필살기 매칭 순위(취업전략 리포트를 참고해서 정리하자.)\n\n`7` 경험리스트업 아쉬운 사례\n\n- 유사경험을 점검해봐야할 경우 : 유사경험과 직무 KPI 매칭이 맞지 않는 경우\n    * 연구개발하는 사람이 축구 1등 해놓고 성능개선한거다...뭐 이런식?\n\n- KPI/경험 매칭이 어색한 경우\n    * 내것도 뭔가 좀 어색하다. $\\to$ 다시 첫 단추부터...ㅜㅜ\n    * 직무 KPI부터 다시 엑셀로 뽑고 계속 갱신하자.\n","srcMarkdownNoYaml":"\n\n# Intro\n\n`1` 3C4P를 2개 정도 잘 정리하자.\n\n`2` 1일 1지원을 목표로! (완벽주의가 아닌 완성주의 마인드 셋)\n\n# 체인지업 기본 참여 마인드셋\n\n`1` GDR-4 중 최합자 vs. 불합격자 비교\n\n- 과제참여도는 전반적으로 높음\n\n- 서류 제출 시기 늦음 : 미최합자의 `62%`는 4주차부터 본격적으로 서류 제출 시작\n    * 완벽주의에 위험성...갖다 버리자\n\n- 3C4P 분해 미흡 : 미최합자의 `50%`는 3C4P 완성도 미흡\n    * **`3C4P`를 `매일 수치화`하고 `매일 디테일`하게 수정하자.**\n    * 포트폴리오도 주차별로 업데이트 하자.(난 매일매일...)\n\n- 중소기업 지원 비율 낮음 : 미최합자의 `50%`는 중소 기업의 지원률이 매우 저조하고 중견이상 지원\n    * 중소기업을 쓰는 이유는 면접 연습이다.\n    * 또한, 다 떨어질 경우를 대비해서 지원하는 것이 좋다.\n- 지원 기업 준비도 미흡 : 미최합자의 `25%`는 각 회사별로 지원동기 작성을 못했거나 포트폴리오 또는 이력서를 자소서보다 우선시 하는 기업 위주로 지원\n\n`2` 결론\n\n- 1주차 부터 지원 시도하자.\n\n- 한번을 하더라도 `영혼을 갈아넣어서` 완성주의 과제를 진행하자.\n\n- 대기업만이 아닌 `대기업도 포함`해서 지원하자.\n\n- 또한, 유튜브도 참고하자.(매일 매일 1개씩 보고 느낀점 기록)\n\n***\n\n# 경험리스트업으로 필살기 발굴\n\n`1` 최종합격자들의 경험리스트업\n\n- 신입은 분류한 총 경험개수 12개, 필살기 경험개수 3개 정도...\n\n`2` 필살기 경험 유형\n\n- 인문계열 경험유형 top3 : `인턴`, 계약직, 아르바이트\n\n- 이공계열 경험유형 top3 : `학교프로젝트`, 연구/개발, 아르바이트\n\n`3` 필살기/KPI 매칭 특징 : `수치화` 가능한 결과물이 있는 경험 `O`\n\n- 인문계열 주요 KPI list : 매출상승(영업), 비용 및 예산준수(회계), 전환율(마케팅)\n\n- 이공계열 주요 KPI list : 불량률 개선(품질관리), 성능개선(공정기술), 프로젝트 완료율(연구개발), 기술스택개선(IT개발)\n\n`4` 최종합격자 경험리스트업케이스 $\\to$ `나에게` 중요한 것이 아닌, `수치화가 된 결과물 위주로 경험 매칭!\n\n- 데이터분석 : KPI 매칭이 1개만 될 경우도 있다. 그래도 걱정하지 말자\n    * 연구개발\n    * 수상경력\n    * 연구개발\n    * 교내 프로젝트\n    * 피드백 : 내가 한 것들을 전부 수치화해서 다시 정리하자  \n\n`6` 필살기 매칭 순위(취업전략 리포트를 참고해서 정리하자.)\n\n`7` 경험리스트업 아쉬운 사례\n\n- 유사경험을 점검해봐야할 경우 : 유사경험과 직무 KPI 매칭이 맞지 않는 경우\n    * 연구개발하는 사람이 축구 1등 해놓고 성능개선한거다...뭐 이런식?\n\n- KPI/경험 매칭이 어색한 경우\n    * 내것도 뭔가 좀 어색하다. $\\to$ 다시 첫 단추부터...ㅜㅜ\n    * 직무 KPI부터 다시 엑셀로 뽑고 계속 갱신하자.\n"},"formats":{"html":{"identifier":{"display-name":"HTML","target-format":"html","base-format":"html"},"execute":{"fig-width":7,"fig-height":5,"fig-format":"retina","fig-dpi":96,"df-print":"default","error":false,"eval":true,"cache":null,"freeze":true,"echo":true,"output":true,"warning":true,"include":true,"keep-md":false,"keep-ipynb":false,"ipynb":null,"enabled":false,"daemon":null,"daemon-restart":false,"debug":false,"ipynb-filters":[],"ipynb-shell-interactivity":null,"plotly-connected":true,"engine":"jupyter"},"render":{"keep-tex":false,"keep-typ":false,"keep-source":false,"keep-hidden":false,"prefer-html":false,"output-divs":true,"output-ext":"html","fig-align":"default","fig-pos":null,"fig-env":null,"code-fold":false,"code-overflow":"scroll","code-link":false,"code-line-numbers":true,"code-tools":false,"tbl-colwidths":"auto","merge-includes":true,"inline-includes":false,"preserve-yaml":false,"latex-auto-mk":true,"latex-auto-install":true,"latex-clean":true,"latex-min-runs":1,"latex-max-runs":10,"latex-makeindex":"makeindex","latex-makeindex-opts":[],"latex-tlmgr-opts":[],"latex-input-paths":[],"latex-output-dir":null,"link-external-icon":false,"link-external-newwindow":false,"self-contained-math":false,"format-resources":[],"notebook-links":true},"pandoc":{"standalone":true,"wrap":"none","default-image-extension":"png","to":"html","css":["../../../styles.css"],"toc":true,"output-file":"1wk.html"},"language":{"toc-title-document":"Table of contents","toc-title-website":"On this page","related-formats-title":"Other Formats","related-notebooks-title":"Notebooks","source-notebooks-prefix":"Source","other-links-title":"Other Links","code-links-title":"Code Links","launch-dev-container-title":"Launch Dev Container","launch-binder-title":"Launch Binder","article-notebook-label":"Article Notebook","notebook-preview-download":"Download Notebook","notebook-preview-download-src":"Download Source","notebook-preview-back":"Back to Article","manuscript-meca-bundle":"MECA Bundle","section-title-abstract":"Abstract","section-title-appendices":"Appendices","section-title-footnotes":"Footnotes","section-title-references":"References","section-title-reuse":"Reuse","section-title-copyright":"Copyright","section-title-citation":"Citation","appendix-attribution-cite-as":"For attribution, please cite this work as:","appendix-attribution-bibtex":"BibTeX citation:","title-block-author-single":"Author","title-block-author-plural":"Authors","title-block-affiliation-single":"Affiliation","title-block-affiliation-plural":"Affiliations","title-block-published":"Published","title-block-modified":"Modified","title-block-keywords":"Keywords","callout-tip-title":"Tip","callout-note-title":"Note","callout-warning-title":"Warning","callout-important-title":"Important","callout-caution-title":"Caution","code-summary":"Code","code-tools-menu-caption":"Code","code-tools-show-all-code":"Show All Code","code-tools-hide-all-code":"Hide All Code","code-tools-view-source":"View Source","code-tools-source-code":"Source Code","tools-share":"Share","tools-download":"Download","code-line":"Line","code-lines":"Lines","copy-button-tooltip":"Copy to Clipboard","copy-button-tooltip-success":"Copied!","repo-action-links-edit":"Edit this page","repo-action-links-source":"View source","repo-action-links-issue":"Report an issue","back-to-top":"Back to top","search-no-results-text":"No results","search-matching-documents-text":"matching documents","search-copy-link-title":"Copy link to search","search-hide-matches-text":"Hide additional matches","search-more-match-text":"more match in this document","search-more-matches-text":"more matches in this document","search-clear-button-title":"Clear","search-text-placeholder":"","search-detached-cancel-button-title":"Cancel","search-submit-button-title":"Submit","search-label":"Search","toggle-section":"Toggle section","toggle-sidebar":"Toggle sidebar navigation","toggle-dark-mode":"Toggle dark mode","toggle-reader-mode":"Toggle reader mode","toggle-navigation":"Toggle navigation","crossref-fig-title":"Figure","crossref-tbl-title":"Table","crossref-lst-title":"Listing","crossref-thm-title":"Theorem","crossref-lem-title":"Lemma","crossref-cor-title":"Corollary","crossref-prp-title":"Proposition","crossref-cnj-title":"Conjecture","crossref-def-title":"Definition","crossref-exm-title":"Example","crossref-exr-title":"Exercise","crossref-ch-prefix":"Chapter","crossref-apx-prefix":"Appendix","crossref-sec-prefix":"Section","crossref-eq-prefix":"Equation","crossref-lof-title":"List of Figures","crossref-lot-title":"List of Tables","crossref-lol-title":"List of Listings","environment-proof-title":"Proof","environment-remark-title":"Remark","environment-solution-title":"Solution","listing-page-order-by":"Order By","listing-page-order-by-default":"Default","listing-page-order-by-date-asc":"Oldest","listing-page-order-by-date-desc":"Newest","listing-page-order-by-number-desc":"High to Low","listing-page-order-by-number-asc":"Low to High","listing-page-field-date":"Date","listing-page-field-title":"Title","listing-page-field-description":"Description","listing-page-field-author":"Author","listing-page-field-filename":"File Name","listing-page-field-filemodified":"Modified","listing-page-field-subtitle":"Subtitle","listing-page-field-readingtime":"Reading Time","listing-page-field-wordcount":"Word Count","listing-page-field-categories":"Categories","listing-page-minutes-compact":"{0} min","listing-page-category-all":"All","listing-page-no-matches":"No matching items","listing-page-words":"{0} words"},"metadata":{"lang":"en","fig-responsive":true,"quarto-version":"1.4.551","theme":{"light":"flatly"},"editor":"visual","code-copy":true,"title-block-banner":true,"title":"00. 1wk","author":"gc","date":"09/11/24"},"extensions":{"book":{"multiFile":true}}}},"projectFormats":["html"]}